{"framework":"apd-framework-9.0.8","title":"Nápověda pro Kalkulačku","build_id":"5592d8e8680ce2fd3574e596","icon":"..\/GlobalArt\/AppIconDefault_Calculator.png","sections":{},"birdseed_version":4,"toc":[],"locale":"cs","version":"10.11","enable_tracking":false,"source_schema":"apd-schema","platform":"mac","build_date":"2015.06.30-11:00:53","landing":"calc34870","product":"calculator","urls":{},"copyright":"","topics":{"calc34870":{"name":"Provádění výpočtů pomocí Kalkulačky","href":"calc34870.html","searchName":"Provádění výpočtů pomocí Kalkulačky"}},"copyright_text":"© 2015 Apple Inc. Všechna práva vyhrazena.","css":""}